bootstrap3/__about__.py
bootstrap3/__init__.py
bootstrap3/bootstrap.py
bootstrap3/components.py
bootstrap3/exceptions.py
bootstrap3/forms.py
bootstrap3/models.py
bootstrap3/renderers.py
bootstrap3/templates/bootstrap3/bootstrap3.html
bootstrap3/templates/bootstrap3/field_error.html
bootstrap3/templates/bootstrap3/field_help_text.html
bootstrap3/templates/bootstrap3/field_help_text_and_errors.html
bootstrap3/templates/bootstrap3/form_errors.html
bootstrap3/templates/bootstrap3/messages.html
bootstrap3/templates/bootstrap3/pagination.html
bootstrap3/templatetags/__init__.py
bootstrap3/templatetags/bootstrap3.py
bootstrap3/text.py
bootstrap3/utils.py
django_bootstrap3-25.3.dist-info/licenses/AUTHORS
django_bootstrap3-25.3.dist-info/licenses/LICENSE
django_bootstrap3-25.3.dist-info/WHEEL
django_bootstrap3-25.3.dist-info/METADATA
django_bootstrap3-25.3.dist-info/RECORD
