Metadata-Version: 2.4
Name: django-bootstrap3
Version: 25.3
Summary: Bootstrap 3 for Django
Keywords: django,bootstrap,bootstrap3
Author: Dylan Verheul
Author-email: Dylan Verheul <dylan@dyve.net>
License-Expression: BSD-3-Clause
License-File: AUTHORS
License-File: LICENSE
Classifier: Development Status :: 5 - Production/Stable
Classifier: Environment :: Web Environment
Classifier: Framework :: Django
Classifier: Framework :: Django :: 4.2
Classifier: Framework :: Django :: 5.1
Classifier: Framework :: Django :: 5.2
Classifier: Framework :: Django :: 6.0
Classifier: Intended Audience :: Developers
Classifier: Operating System :: OS Independent
Classifier: Programming Language :: Python :: 3
Classifier: Programming Language :: Python :: 3.10
Classifier: Programming Language :: Python :: 3.11
Classifier: Programming Language :: Python :: 3.12
Classifier: Programming Language :: Python :: 3.13
Classifier: Programming Language :: Python :: 3.14
Classifier: Topic :: Software Development :: Libraries
Classifier: Topic :: Utilities
Requires-Dist: django>=4.2
Requires-Python: >=3.10
Project-URL: Changelog, https://github.com/zostera/django-bootstrap3/blob/main/CHANGELOG.md
Project-URL: Documentation, https://django-bootstrap3.readthedocs.io/
Project-URL: Homepage, https://github.com/zostera/django-bootstrap3
Project-URL: Issues, https://github.com/zostera/django-bootstrap3/issues
Project-URL: Source, https://github.com/zostera/django-bootstrap3
